oasis/__init__.py
oasis/druck.py
oasis/experiments.py
oasis/input_verification.py
oasis/oasis.py
oasis/passive.py
oasis/sawade.py
oasis/stratification.py
oasis-0.1.3.dist-info/LICENSE
oasis-0.1.3.dist-info/METADATA
oasis-0.1.3.dist-info/WHEEL
oasis-0.1.3.dist-info/top_level.txt
oasis-0.1.3.dist-info/RECORD
