Metadata-Version: 2.1
Name: oasis
Version: 0.1.3
Summary: Optimal Asymptotic Sequential Importance Sampling
Home-page: http://ngmarchant.github.io/oasis
Author: Neil G. Marchant
Author-email: ngmarchant@gmail.com
License: MIT
Keywords: F-measure active sampling evaluation classification recall precision
Platform: UNKNOWN
Classifier: Intended Audience :: Science/Research
Classifier: License :: OSI Approved :: MIT License
Classifier: Programming Language :: Python
Classifier: Topic :: Software Development
Classifier: Topic :: Scientific/Engineering
Classifier: Topic :: Scientific/Engineering :: Artificial Intelligence
Classifier: Programming Language :: Python :: 3
License-File: LICENSE
Requires-Dist: numpy
Requires-Dist: tables
Requires-Dist: scipy
Requires-Dist: sklearn
